{"https://j-island.net/movie/play/id/2353": "中村嶺亜 (7 MEN 侍)、鎌田凌成「身長差…!?」", "https://j-island.net/movie/play/id/2351": "中村嶺亜、横原悠毅、作間龍斗「よこれあチャンネル⑳」", "https://j-island.net/movie/play/id/1799": "菅田琳寧、谷村龍一「なんと!?」", "https://j-island.net/movie/play/id/1798": "菅田琳寧、谷村龍一「谷村くん...!?」", "https://j-island.net/movie/play/id/1797": "菅田琳寧、谷村龍一「一発ギャグ」", "https://j-island.net/movie/play/id/1796": "菅田琳寧、谷村龍一「レッスンとリハ終わりに」", "https://j-island.net/movie/play/id/2219": "菅田琳寧、矢花黎「弟」", "https://j-island.net/movie/play/id/2218": "橋本涼、作間龍斗、菅田琳寧、本髙克樹「本番前恒例の筋トレ《腹筋編》」", "https://j-island.net/movie/play/id/2068": "中村嶺亜、織山尚大、小柴陸「恋の病と野郎組の3人」", "https://j-island.net/movie/play/id/2211": "7 MEN 侍「本番前①」", "https://j-island.net/movie/play/id/2210": "佐々木大光、髙橋優斗「本番９分前」", "https://j-island.net/movie/play/id/2217": "橋本涼、作間龍斗、菅田琳寧、本髙克樹「本番前恒例の筋トレ《腕立て編》」", "https://j-island.net/movie/play/id/2216": "佐々木大光、今野大輝「新年のご挨拶」", "https://j-island.net/movie/play/id/1401": "菅田琳寧、本髙克樹、谷村龍一、松井奏「レッスン終わり」", "https://j-island.net/movie/play/id/2214": "HiHi Jets、7 MEN 侍「円陣」", "https://j-island.net/movie/play/id/2199": "松尾龍、中村浩大、今村隼人、菅田琳寧 「パパママ一番 裸の少年 夏祭り！」８分前", "https://j-island.net/movie/play/id/1967": "矢花黎 、和田優希「当日の朝です！」", "https://j-island.net/movie/play/id/1568": "佐々木大光、谷村龍一「せっせっせーのよいよいよい」", "https://j-island.net/movie/play/id/1788": "今野大輝、矢花黎、末武幸紘、髙橋汐音「高校の思い出」", "https://j-island.net/movie/play/id/465": "今野大輝、中村浩大「タイムマシン」", "https://j-island.net/movie/play/id/1550": "矢花黎「矢花劇場②」", "https://j-island.net/movie/play/id/1803": "佐々木大光、谷村龍一「スローモーション」", "https://j-island.net/movie/play/id/1802": "本髙克樹、谷村龍一「良い声で」", "https://j-island.net/movie/play/id/1801": "本髙克樹、谷村龍一「久しぶり！」", "https://j-island.net/movie/play/id/1800": "菅田琳寧、谷村龍一、末武幸紘「あれ？背が...!?」", "https://j-island.net/movie/play/id/1146": "Jr.SP、菅田琳寧、今野大輝 「龍セット」", "https://j-island.net/movie/play/id/2206": "矢花黎「パパママ一番 裸の少年 夏祭り！」楽器紹介", "https://j-island.net/movie/play/id/2207": "HiHi Jets、7 MEN 侍「パパママ一番 裸の少年 夏祭り！」MC", "name": "佐々木大光", "https://j-island.net/movie/play/id/359": "7 MEN 侍「新学期」", "https://j-island.net/movie/play/id/358": "7 MEN 侍「ちっちゃくなっちゃった！」", "https://j-island.net/movie/play/id/1307": "佐々木大光、矢花黎「ブロワー」", "https://j-island.net/movie/play/id/1308": "7 MEN 侍、矢後敦海「楽器隊」", "https://j-island.net/movie/play/id/1309": "今野大輝、中村浩大「愛について」", "https://j-island.net/movie/play/id/1548": "佐々木大光、矢花黎「痛い！」", "https://j-island.net/movie/play/id/1549": "矢花黎「矢花劇場①」", "https://j-island.net/movie/play/id/2040": "菅田琳寧、浮所飛貴、橋本涼「スペシャルゲストの鎖骨」", "https://j-island.net/movie/play/id/2041": "菅田琳寧、藤井直樹「ハグ」", "https://j-island.net/movie/play/id/755": "菅田琳寧「ひょっこ…」", "https://j-island.net/movie/play/id/754": "菅田琳寧「特に何もない動画」", "https://j-island.net/movie/play/id/2239": "少年忍者、菅田琳寧「オーラ（オープンライブだけに）」", "https://j-island.net/movie/play/id/750": "中村嶺亜、横原悠毅「よこれあチャンネル④」", "https://j-island.net/movie/play/id/291": "川島、本髙、渡辺、寺西、松倉、松田「Endless SHOCK」終演後", "https://j-island.net/movie/play/id/923": "佐々木大光、矢花黎「佐々木大光を探せ」", "https://j-island.net/movie/play/id/1133": "中村嶺亜、横原悠毅「よこれあチャンネル⑩」", "https://j-island.net/movie/play/id/1132": "中村嶺亜、織山尚大「ハイテンション」", "https://j-island.net/movie/play/id/1131": "菅田琳寧、久保廉「〇〇ですっ！」", "https://j-island.net/movie/play/id/1422": "7 MEN 侍「レモン」", "https://j-island.net/movie/play/id/1424": "7 MEN 侍「矢花くんが…」", "https://j-island.net/movie/play/id/1403": "矢花黎 「お弁当」", "https://j-island.net/movie/play/id/1402": "菅田琳寧、鈴木舜映、本髙克樹、松井奏「KAT-TUN上田くんへ」", "https://j-island.net/movie/play/id/2215": "7 MEN 侍「今日のすげた」", "https://j-island.net/movie/play/id/85": "本番前の円陣@TOKYO DOME CITY HALL", "https://j-island.net/movie/play/id/1400": "菅田琳寧、本髙克樹「君と…Milky way」", "https://j-island.net/movie/play/id/2222": "佐々木大光「変顔」", "https://j-island.net/movie/play/id/2220": "菅田琳寧「アイスをただ食べる動画」", "https://j-island.net/movie/play/id/2221": "佐々木大光「キメ顔」", "https://j-island.net/movie/play/id/723": "矢花黎、和田優希、森永祐二「見学」", "https://j-island.net/movie/play/id/2228": "菅田琳寧「本番前②」", "https://j-island.net/movie/play/id/2135": "矢花黎、髙橋真斗「いただきもの」", "https://j-island.net/movie/play/id/1944": "本髙克樹、今野大輝、矢花黎「東京ドーム公演前日！」", "https://j-island.net/movie/play/id/1942": "浮所飛貴、本髙克樹、大西流星「こんにちは！」", "https://j-island.net/movie/play/id/1943": "浮所飛貴、本髙克樹、今野大輝、末武幸紘「リハ中だよ！」", "https://j-island.net/movie/play/id/1124": "中村嶺亜、Jr.SP「クリエ本番前」", "https://j-island.net/movie/play/id/1126": "菅田琳寧、谷村龍一「クリエ本番前」", "https://j-island.net/movie/play/id/236": "中村嶺亜、菅田琳寧「Snow Manライブ前」", "https://j-island.net/movie/play/id/237": "中村嶺亜、横原悠毅「仲良し」", "https://j-island.net/movie/play/id/1829": "中村嶺亜 、横原悠毅「よこれあチャンネル⑩その2」", "https://j-island.net/movie/play/id/607": "菅田琳寧「令和」", "https://j-island.net/movie/play/id/1828": "7 MEN 侍「スケートボード」", "https://j-island.net/movie/play/id/2079": "七五三掛龍也、藤井直樹、中村嶺亜、大西流星「ジャニーズ喫茶」", "https://j-island.net/movie/play/id/1055": "矢花黎「廃墟!?」", "https://j-island.net/movie/play/id/1057": "佐々木大光、菅田琳寧、矢花黎、本髙克樹「変顔②」", "https://j-island.net/movie/play/id/2149": "7 MEN 侍「発表！」", "https://j-island.net/movie/play/id/1053": "矢花黎「変顔①」", "https://j-island.net/movie/play/id/1830": "矢花黎「ロッカーのどこかに…」", "https://j-island.net/movie/play/id/2141": "佐々木大光、作間龍斗、大西流星「東京ドーム公演ステージ裏で、大西くんにクイズ！」", "https://j-island.net/movie/play/id/131": "今野大輝、松尾龍「髪セット」", "https://j-island.net/movie/play/id/193": "中村嶺亜、本髙克樹、矢花黎、林蓮音、松尾龍「SixTONES開演3分前」", "https://j-island.net/movie/play/id/548": "7 MEN 侍「検証」", "https://j-island.net/movie/play/id/1348": "矢花黎「ドラム」", "https://j-island.net/movie/play/id/1107": "Jr.SP、矢花黎、今野大輝、林拓音、髙橋汐音「クリエ楽屋にて」", "https://j-island.net/movie/play/id/1105": "Jr.SP「クリエ本番前」", "https://j-island.net/movie/play/id/547": "7 MEN 侍「速報」", "https://j-island.net/movie/play/id/2363": "美 少年、7 MEN 侍「YouTubeの撮影です！」", "https://j-island.net/movie/play/id/2362": "美 少年、7 MEN 侍「美 少年で～す？」", "https://j-island.net/movie/play/id/961": "7 MEN 侍「SAMURAI」コールver.レクチャー", "https://j-island.net/movie/play/id/789": "菅田琳寧、本髙克樹「スーツ」", "https://j-island.net/movie/play/id/1582": "矢花黎「矢花バンド」", "https://j-island.net/movie/play/id/146": "矢花黎「魚の神」", "https://j-island.net/movie/play/id/1504": "今村隼人、矢花黎、林蓮音、和田優希、林拓音「祝！ハタチ！」", "https://j-island.net/movie/play/id/805": "今野大輝、中村浩大「ミソスープ」", "https://j-island.net/movie/play/id/2161": "7 MEN 侍「パパママ一番 裸の少年 夏祭り！」お楽しみに！", "https://j-island.net/movie/play/id/1917": "7 MEN 侍「ジャニーズJr.８・８祭り ～東京ドームから始まる～」", "https://j-island.net/movie/play/id/1072": "7 MEN 侍、西村拓哉、大西風雅「佐々木大光 vs 大西風雅」", "https://j-island.net/movie/play/id/1423": "佐々木大光、矢花黎「佐々木大光を探せ」", "https://j-island.net/movie/play/id/798": "7 MEN 侍「菅田の日」", "https://j-island.net/movie/play/id/363": "7 MEN 侍「自主練②紹介」", "https://j-island.net/movie/play/id/2170": "本髙克樹、矢花黎「ラップ」", "https://j-island.net/movie/play/id/2171": "菅田琳寧、本髙克樹「YouTube見てくれた？」", "https://j-island.net/movie/play/id/1161": "中村嶺亜、本髙克樹「見せ場」", "https://j-island.net/movie/play/id/1162": "矢花黎「楽器紹介」", "https://j-island.net/movie/play/id/1086": "矢花黎、Jr.SP「楽屋突撃！」", "https://j-island.net/movie/play/id/1085": "7 MEN 侍「TAKE ME HIGHER」振付講座", "https://j-island.net/movie/play/id/374": "今野大輝、中村浩大「キッス～帰り道のラブソング～」"}